aq_geometric/__init__.py
aq_geometric/data/__init__.py
aq_geometric/data/file/__init__.py
aq_geometric/data/file/local.py
aq_geometric/data/filter/__init__.py
aq_geometric/data/filter/node_features.py
aq_geometric/data/graph/__init__.py
aq_geometric/data/graph/compute_graph.py
aq_geometric/data/graph/graphs_builder.py
aq_geometric/data/graph/edges/__init__.py
aq_geometric/data/graph/edges/compute_edges.py
aq_geometric/data/graph/nodes/__init__.py
aq_geometric/data/graph/nodes/compute_node_features.py
aq_geometric/data/graph/nodes/compute_nodes.py
aq_geometric/data/reindex/__init__.py
aq_geometric/data/reindex/features.py
aq_geometric/data/remote/__init__.py
aq_geometric/data/remote/psql.py
aq_geometric/datasets/__init__.py
aq_geometric/datasets/adapters/base_adapter.py
aq_geometric/datasets/adapters/numpy/aq_geometric_dataset.py
aq_geometric/datasets/adapters/onnx/aq_geometric_dataset.py
aq_geometric/datasets/adapters/torch/aq_geometric_dataset.py
aq_geometric/datasets/in_memory/__init__.py
aq_geometric/datasets/in_memory/aq_geometric_dataset.py
aq_geometric/datasets/on_disk/aq_geometric_dataset.py
aq_geometric/datasets/utilities/__init__.py
aq_geometric/datasets/utilities/data/__init__.py
aq_geometric/datasets/utilities/data/transforms.py
aq_geometric/metrics/metrics.py
aq_geometric/models/__init__.py
aq_geometric/models/base_model.py
aq_geometric/models/test_base_model.py
aq_geometric/models/lightgbm/__init__.py
aq_geometric/models/lightgbm/base_lgbm_model.py
aq_geometric/models/lightgbm/hierarchical_lgb/__init__.py
aq_geometric/models/lightgbm/hierarchical_lgb/base_hierarchical_lgb.py
aq_geometric/models/lightgbm/hierarchical_lgb/hierarchical_lgb_direct.py
aq_geometric/models/lightgbm/hierarchical_lgb/hierarchical_lgb_iterative.py
aq_geometric/models/statistical_baselines/__init__.py
aq_geometric/models/statistical_baselines/climatology/climatology.py
aq_geometric/models/statistical_baselines/history/history.py
aq_geometric-2024.9.2.1.dist-info/METADATA
aq_geometric-2024.9.2.1.dist-info/WHEEL
aq_geometric-2024.9.2.1.dist-info/licenses/LICENSE.md
aq_geometric-2024.9.2.1.dist-info/RECORD
